dash_loading_extras/__init__.py
dash_loading_extras/_version.py
dash_loading_extras/packagedassets/shimmer.css
dash_loading_extras-0.1.3.dist-info/LICENSE
dash_loading_extras-0.1.3.dist-info/METADATA
dash_loading_extras-0.1.3.dist-info/WHEEL
dash_loading_extras-0.1.3.dist-info/top_level.txt
dash_loading_extras-0.1.3.dist-info/RECORD
