Metadata-Version: 2.1
Name: dash-loading-extras
Version: 0.1.3
Summary: UNKNOWN
License: UNKNOWN
Platform: UNKNOWN
License-File: LICENSE
Requires-Dist: dash
Requires-Dist: flask
Requires-Dist: importlib-metadata ; python_version == "3.7"
